k3_addons/__init__.py
k3_addons/activations/__init__.py
k3_addons/layers/__init__.py
k3_addons/losses/__init__.py
k3_addons/src/__init__.py
k3_addons/src/api_export.py
k3_addons/src/version.py
k3_addons/src/activations/__init__.py
k3_addons/src/activations/hardshrink.py
k3_addons/src/activations/lisht.py
k3_addons/src/activations/mish.py
k3_addons/src/activations/snake.py
k3_addons/src/activations/tanshrink.py
k3_addons/src/layers/__init__.py
k3_addons/src/layers/attention/__init__.py
k3_addons/src/layers/attention/a2a.py
k3_addons/src/layers/attention/aft.py
k3_addons/src/layers/attention/bam.py
k3_addons/src/layers/attention/cbam.py
k3_addons/src/layers/attention/eca.py
k3_addons/src/layers/attention/external_attention.py
k3_addons/src/layers/attention/mobilevit.py
k3_addons/src/layers/attention/mobilevit_v2.py
k3_addons/src/layers/attention/parnet.py
k3_addons/src/layers/attention/residual.py
k3_addons/src/layers/attention/se.py
k3_addons/src/layers/attention/simam.py
k3_addons/src/layers/normalization/__init__.py
k3_addons/src/layers/normalization/instance_normalization.py
k3_addons/src/layers/pooling/__init__.py
k3_addons/src/layers/pooling/adaptive_pooling.py
k3_addons/src/layers/pooling/maxout.py
k3_addons/src/losses/__init__.py
k3_addons/src/losses/contrastive_loss.py
k3_addons/src/losses/focal_loss.py
k3_addons/src/losses/giou_loss.py
k3_addons/src/losses/kappa_loss.py
k3_addons/src/losses/metric_learning.py
k3_addons/src/losses/quantiles.py
k3_addons/src/utils/__init__.py
k3_addons/src/utils/keras_utils.py
k3_addons/src/utils/misc.py
k3_addons-0.0.2.dist-info/METADATA
k3_addons-0.0.2.dist-info/WHEEL
k3_addons-0.0.2.dist-info/top_level.txt
k3_addons-0.0.2.dist-info/RECORD
