Metadata-Version: 2.1
Name: k3_addons
Version: 0.0.2
Summary: Making Keras Equivalent to PyTorch
Home-page: https://github.com/anas-rz/k3-addons
Author: Muhammad Anas Raza
Author-email: memanasraza@gmail.com
License: Apache License 2.0
Classifier: Development Status :: 4 - Beta
Classifier: Programming Language :: Python :: 3
Classifier: Programming Language :: Python :: 3.9
Classifier: Programming Language :: Python :: 3.10
Classifier: Programming Language :: Python :: 3.11
Classifier: Programming Language :: Python :: 3 :: Only
Classifier: Operating System :: Unix
Classifier: Operating System :: MacOS
Classifier: Intended Audience :: Science/Research
Classifier: Topic :: Scientific/Engineering
Classifier: Topic :: Software Development
Requires-Python: >=3.9
Requires-Dist: keras >=3.0.5
